bhargabchipkg/__init__.py
bhargabchipkg/chitest_rs.py
bhargabchipkg-0.1.0.dist-info/LICENSE
bhargabchipkg-0.1.0.dist-info/METADATA
bhargabchipkg-0.1.0.dist-info/WHEEL
bhargabchipkg-0.1.0.dist-info/top_level.txt
bhargabchipkg-0.1.0.dist-info/RECORD
